MANIFEST.in
Makefile
README.rst
ez_setup.py
gittaggers.py
setup.cfg
setup.py
cwltool/__init__.py
cwltool/__main__.py
cwltool/builder.py
cwltool/cwlrdf.py
cwltool/cwltest.py
cwltool/docker.py
cwltool/docker_uid.py
cwltool/draft2tool.py
cwltool/errors.py
cwltool/expression.py
cwltool/factory.py
cwltool/flatten.py
cwltool/job.py
cwltool/load_tool.py
cwltool/main.py
cwltool/pathmapper.py
cwltool/process.py
cwltool/sandboxjs.py
cwltool/stdfsaccess.py
cwltool/update.py
cwltool/utils.py
cwltool/workflow.py
cwltool/schemas/draft-2/CommonWorkflowLanguage.yml
cwltool/schemas/draft-2/cwl-avro.yml
cwltool/schemas/draft-3/CommandLineTool-standalone.yml
cwltool/schemas/draft-3/CommandLineTool.yml
cwltool/schemas/draft-3/CommonWorkflowLanguage.yml
cwltool/schemas/draft-3/Process.yml
cwltool/schemas/draft-3/README.md
cwltool/schemas/draft-3/UserGuide.yml
cwltool/schemas/draft-3/Workflow.yml
cwltool/schemas/draft-3/concepts.md
cwltool/schemas/draft-3/contrib.md
cwltool/schemas/draft-3/index.yml
cwltool/schemas/draft-3/intro.md
cwltool/schemas/draft-3/invocation.md
cwltool/schemas/draft-3/userguide-intro.md
cwltool/schemas/draft-3/salad/schema_salad/metaschema/field_name.yml
cwltool/schemas/draft-3/salad/schema_salad/metaschema/field_name_proc.yml
cwltool/schemas/draft-3/salad/schema_salad/metaschema/field_name_schema.yml
cwltool/schemas/draft-3/salad/schema_salad/metaschema/field_name_src.yml
cwltool/schemas/draft-3/salad/schema_salad/metaschema/ident_res.yml
cwltool/schemas/draft-3/salad/schema_salad/metaschema/ident_res_proc.yml
cwltool/schemas/draft-3/salad/schema_salad/metaschema/ident_res_schema.yml
cwltool/schemas/draft-3/salad/schema_salad/metaschema/ident_res_src.yml
cwltool/schemas/draft-3/salad/schema_salad/metaschema/import_include.md
cwltool/schemas/draft-3/salad/schema_salad/metaschema/link_res.yml
cwltool/schemas/draft-3/salad/schema_salad/metaschema/link_res_proc.yml
cwltool/schemas/draft-3/salad/schema_salad/metaschema/link_res_schema.yml
cwltool_ucsc.egg-info/PKG-INFO
cwltool_ucsc.egg-info/SOURCES.txt
cwltool_ucsc.egg-info/dependency_links.txt
cwltool_ucsc.egg-info/entry_points.txt
cwltool_ucsc.egg-info/requires.txt
cwltool_ucsc.egg-info/top_level.txt
cwltool_ucsc.egg-info/zip-safe