Metadata-Version: 1.1
Name: cwltool-ucsc
Version: 1.36.20161114152756
Summary: Common workflow language reference implementation patched for UCSC-CGL
Home-page: https://github.com/tboser/cwltool
Author: Common workflow language working group
Author-email: common-workflow-language@googlegroups.com
License: Apache 2.0
Download-URL: https://github.com/tboser/cwltool
Platform: UNKNOWN
